sc_simvar-0.3.1.dist-info/METADATA
sc_simvar-0.3.1.dist-info/WHEEL
sc_simvar-0.3.1.dist-info/licenses/AUTHORS.md
sc_simvar-0.3.1.dist-info/licenses/LICENSE.md
sc_simvar/__init__.py
sc_simvar/_config.py
sc_simvar/_lib.cpython-312-aarch64-linux-gnu.so
sc_simvar/_lib.pyi
sc_simvar/_not_yet_rust/__init__.py
sc_simvar/_not_yet_rust/_assign_modules.py
sc_simvar/_not_yet_rust/_assign_modules_core.py
sc_simvar/_not_yet_rust/_calc_mean_dists.py
sc_simvar/_not_yet_rust/_compute_modules.py
sc_simvar/_not_yet_rust/_compute_scores.py
sc_simvar/_not_yet_rust/_create_centered_counts_row.py
sc_simvar/_not_yet_rust/_distances_neighbors_and_weights.py
sc_simvar/_not_yet_rust/_latent_neighbors_and_weights.py
sc_simvar/_not_yet_rust/_local_correlation_plot.py
sc_simvar/_not_yet_rust/_neighbor_smoothing_row.py
sc_simvar/_not_yet_rust/_sort_linkage.py
sc_simvar/_not_yet_rust/_tree_neighbors_and_weights.py
sc_simvar/_not_yet_rust/_tree_node.py
sc_simvar/_sc_simvar.py
sc_simvar/_types.py
sc_simvar/py.typed
sc_simvar-0.3.1.dist-info/RECORD
