Metadata-Version: 2.4
Name: sc_simvar
Version: 0.3.1
Requires-Dist: anndata>=0.8.0
Requires-Dist: matplotlib>=3.0.0
Requires-Dist: numpy>=1.16.4
Requires-Dist: pandas>=1.0.0
Requires-Dist: scipy>=1.2.1
Requires-Dist: tqdm>=4.32.2
Requires-Dist: numba>=0.43.1
Requires-Dist: pynndescent>=0.5.11
Requires-Dist: scikit-learn>=0.21.2
Requires-Dist: ete3>=3.1.3 ; extra == 'tree'
Provides-Extra: tree
License-File: LICENSE.md
License-File: AUTHORS.md
Summary: A re-implementation of the hotspotsc package using wrappers around Rust code.
Author-email: Max Hargreaves <hargreaw@gene.com>
License: MIT
Requires-Python: >=3.10
Project-URL: Homepage, https://genentech.github.io/sc_simvar/
Project-URL: Repository, https://github.com/Genentech/sc_simvar
